py_helper.py
py_helper_mod-0.0.57.dist-info/licenses/LICENSE
py_helper_mod-0.0.57.dist-info/METADATA
py_helper_mod-0.0.57.dist-info/WHEEL
py_helper_mod-0.0.57.dist-info/top_level.txt
py_helper_mod-0.0.57.dist-info/RECORD
