Metadata-Version: 2.4
Name: py-helper-mod
Version: 0.0.57
Summary: Python Helper Module for my Use
Home-page: https://github.com/ejohnfel/py_helper
Author: Eric Johnfelt
Author-email: Eric Johnfelt <ejohnfel@hotmail.com>
Maintainer-email: Eric Johnfelt <ejohnfel@hotmail.com>
License-Expression: MIT
Project-URL: Homepage, https://github.com/ejohnfel/py_helper
Project-URL: Repository, https://github.com/ejohnfel/py_helper
Project-URL: Bug Traccker, https://github.com/ejohnfel/py_helper/issues
Classifier: Programming Language :: Python :: 3
Classifier: Operating System :: OS Independent
Requires-Python: >=3.8
License-File: LICENSE
Dynamic: license-file
